README.md
setup.cfg
setup.py
dq_whistler/__init__.py
dq_whistler/analyzer.py
dq_whistler/main.py
dq_whistler.egg-info/PKG-INFO
dq_whistler.egg-info/SOURCES.txt
dq_whistler.egg-info/dependency_links.txt
dq_whistler.egg-info/requires.txt
dq_whistler.egg-info/top_level.txt
dq_whistler/constraints/__init__.py
dq_whistler/constraints/constraint.py
dq_whistler/constraints/number_type.py
dq_whistler/constraints/string_type.py
dq_whistler/data_sources/__init__.py
dq_whistler/data_sources/data_source.py
dq_whistler/data_sources/file_source.py
dq_whistler/profiler/__init__.py
dq_whistler/profiler/column_profiler.py
dq_whistler/profiler/number_profiler.py
dq_whistler/profiler/string_profiler.py
tests/__init__.py
tests/dq_whistler/__init__.py
tests/dq_whistler/test_runner.py
tests/dq_whistler/constraints/__init__.py
tests/dq_whistler/constraints/test_number_constraints.py
tests/dq_whistler/constraints/test_string_constraints.py